calculatorpython/__init__.py
calculatorpython/add.py
calculatorpython/divide.py
calculatorpython/multiply.py
calculatorpython/subtract.py
calculatorpython-0.0.4.dist-info/License.txt
calculatorpython-0.0.4.dist-info/METADATA
calculatorpython-0.0.4.dist-info/WHEEL
calculatorpython-0.0.4.dist-info/top_level.txt
calculatorpython-0.0.4.dist-info/RECORD
