Metadata-Version: 2.1
Name: calculatorpython
Version: 0.0.4
Summary: Basic calculator
Home-page: UNKNOWN
Author: Advait Shiralkar
Author-email: advaitshiralkar2@gmail.com
License: UNKNOWN
Platform: UNKNOWN
Classifier: Development Status :: 1 - Planning
Classifier: Intended Audience :: Developers
Classifier: Programming Language :: Python :: 3
Classifier: Operating System :: Unix
Classifier: Operating System :: MacOS :: MacOS X
Classifier: Operating System :: Microsoft :: Windows
License-File: License.txt
Requires-Dist: Calculator
Requires-Dist: vidstream
Requires-Dist: os
Requires-Dist: say-hi
